garaprod/__init__.py
garaprod/modules.py
garaprod/version.py
garastem/__init__ copy.py
garastem/__init__.py
garastem/modules.py
garastem/version.py
garaprod-0.1683618433.0.dist-info/METADATA
garaprod-0.1683618433.0.dist-info/WHEEL
garaprod-0.1683618433.0.dist-info/top_level.txt
garaprod-0.1683618433.0.dist-info/RECORD
